{
  "project_info": {
    "project_number": "108517378329",
    "firebase_url": "https://flash-pdf-card-default-rtdb.firebaseio.com",
    "project_id": "flash-pdf-card",
    "storage_bucket": "flash-pdf-card.appspot.com"
  },
  "client": [
    {
      "client_info": {
        "mobilesdk_app_id": "1:108517378329:android:b197e8ac5195d9c494dd88",
        "android_client_info": {
          "package_name": "ankiapp.site.ai_flash_card"
        }
      },
      "oauth_client": [
        {
          "client_id": "108517378329-4h7vsljelbih1svda4f1ikc50js39qd2.apps.googleusercontent.com",
          "client_type": 3
        }
      ],
      "api_key": [
        {
          "current_key": "AIzaSyDbF3FZ5kUeBoeaZykVv0UFeJBj2V0qqnM"
        }
      ],
      "services": {
        "appinvite_service": {
          "other_platform_oauth_client": [
            {
              "client_id": "108517378329-4h7vsljelbih1svda4f1ikc50js39qd2.apps.googleusercontent.com",
              "client_type": 3
            },
            {
              "client_id": "108517378329-bentvou74e7nqa7gik45dfofapmg7som.apps.googleusercontent.com",
              "client_type": 2,
              "ios_info": {
                "bundle_id": "ankiapp.site.flashPdfCard"
              }
            }
          ]
        }
      }
    },
    {
      "client_info": {
        "mobilesdk_app_id": "1:108517378329:android:87c38bd6e4ad578e94dd88",
        "android_client_info": {
          "package_name": "ankiapp.site.flash_pdf_card"
        }
      },
      "oauth_client": [
        {
          "client_id": "108517378329-4h7vsljelbih1svda4f1ikc50js39qd2.apps.googleusercontent.com",
          "client_type": 3
        }
      ],
      "api_key": [
        {
          "current_key": "AIzaSyDbF3FZ5kUeBoeaZykVv0UFeJBj2V0qqnM"
        }
      ],
      "services": {
        "appinvite_service": {
          "other_platform_oauth_client": [
            {
              "client_id": "108517378329-4h7vsljelbih1svda4f1ikc50js39qd2.apps.googleusercontent.com",
              "client_type": 3
            },
            {
              "client_id": "108517378329-bentvou74e7nqa7gik45dfofapmg7som.apps.googleusercontent.com",
              "client_type": 2,
              "ios_info": {
                "bundle_id": "ankiapp.site.flashPdfCard"
              }
            }
          ]
        }
      }
    }
  ],
  "configuration_version": "1"
}
